README.md
setup.py
dv_elt_lib/ch_ulits.py
dv_elt_lib/gp_ch_utils.py
dv_elt_lib/gp_utils.py
dv_elt_lib.egg-info/PKG-INFO
dv_elt_lib.egg-info/SOURCES.txt
dv_elt_lib.egg-info/dependency_links.txt
dv_elt_lib.egg-info/requires.txt
dv_elt_lib.egg-info/top_level.txt