Metadata-Version: 2.1
Name: dv-elt-lib
Version: 0.0.7
Summary: Python lib to work with databases Greenplum and Clickhouse
Home-page: https://gitlab.com/dv_group/dv_elt_lib
Author: Mark Poroshin
Author-email: mark.poroshin@yandex.ru
License: UNKNOWN
Platform: UNKNOWN
Classifier: Development Status :: 4 - Beta
Classifier: Intended Audience :: Developers
Classifier: Topic :: Software Development :: Build Tools
Classifier: License :: OSI Approved :: MIT License
Classifier: Programming Language :: Python :: 3
Classifier: Programming Language :: Python :: 3.4
Classifier: Programming Language :: Python :: 3.5
Classifier: Programming Language :: Python :: 3.6
